deepbayes/__init__.py
deepbayes/posteriormodel.py
deepbayes/analyzers/__init__.py
deepbayes/analyzers/attacks.py
deepbayes/analyzers/bpda.py
deepbayes/analyzers/intersectionpatch.py
deepbayes/analyzers/probverification.py
deepbayes/analyzers/uncertainty.py
deepbayes/analyzers/verifiers.py
deepbayes/optimizers/__init__.py
deepbayes/optimizers/adam.py
deepbayes/optimizers/bayesbybackprop.py
deepbayes/optimizers/blrvi.py
deepbayes/optimizers/hmc.py
deepbayes/optimizers/losses.py
deepbayes/optimizers/noisyadam.py
deepbayes/optimizers/optimizer.py
deepbayes/optimizers/sgd.py
deepbayes/optimizers/sghmc.py
deepbayes/optimizers/swag.py
deepbayes/optimizers/vogn1.py
deepbayes-0.1.0.dist-info/METADATA
deepbayes-0.1.0.dist-info/WHEEL
deepbayes-0.1.0.dist-info/top_level.txt
deepbayes-0.1.0.dist-info/RECORD
